superset/__init__.py
superset/app.py
superset/config.py
superset/constants.py
superset/dataframe.py
superset/errors.py
superset/exceptions.py
superset/forms.py
superset/jinja_context.py
superset/legacy.py
superset/result_set.py
superset/schemas.py
superset/sql_lab.py
superset/sql_parse.py
superset/stats_logger.py
superset/superset_typing.py
superset/viz.py
superset/advanced_data_type/__init__.py
superset/advanced_data_type/api.py
superset/advanced_data_type/schemas.py
superset/advanced_data_type/types.py
superset/advanced_data_type/plugins/__init__.py
superset/advanced_data_type/plugins/internet_address.py
superset/advanced_data_type/plugins/internet_port.py
superset/annotation_layers/__init__.py
superset/annotation_layers/api.py
superset/annotation_layers/dao.py
superset/annotation_layers/filters.py
superset/annotation_layers/schemas.py
superset/annotation_layers/annotations/__init__.py
superset/annotation_layers/annotations/api.py
superset/annotation_layers/annotations/dao.py
superset/annotation_layers/annotations/filters.py
superset/annotation_layers/annotations/schemas.py
superset/annotation_layers/annotations/commands/__init__.py
superset/annotation_layers/annotations/commands/bulk_delete.py
superset/annotation_layers/annotations/commands/create.py
superset/annotation_layers/annotations/commands/delete.py
superset/annotation_layers/annotations/commands/exceptions.py
superset/annotation_layers/annotations/commands/update.py
superset/annotation_layers/commands/__init__.py
superset/annotation_layers/commands/bulk_delete.py
superset/annotation_layers/commands/create.py
superset/annotation_layers/commands/delete.py
superset/annotation_layers/commands/exceptions.py
superset/annotation_layers/commands/update.py
superset/async_events/__init__.py
superset/async_events/api.py
superset/cachekeys/__init__.py
superset/cachekeys/api.py
superset/cachekeys/schemas.py
superset/charts/__init__.py
superset/charts/api.py
superset/charts/dao.py
superset/charts/filters.py
apache_superset_qwerty-2.0.11.dist-info/LICENSE.txt
apache_superset_qwerty-2.0.11.dist-info/METADATA
apache_superset_qwerty-2.0.11.dist-info/NOTICE
apache_superset_qwerty-2.0.11.dist-info/WHEEL
apache_superset_qwerty-2.0.11.dist-info/entry_points.txt
apache_superset_qwerty-2.0.11.dist-info/top_level.txt
apache_superset_qwerty-2.0.11.dist-info/RECORD
