Metadata-Version: 2.1
Name: apache-superset-qwerty
Version: 2.0.11
Summary: A modern, enterprise-ready business intelligence web application
Home-page: https://superset.apache.org/
Download-URL: https://www.apache.org/dist/superset/2.0.11
Author: Apache Software Foundation
Author-email: dev@superset.apache.org
License: Apache License, Version 2.0
Classifier: Programming Language :: Python :: 3.8
Classifier: Programming Language :: Python :: 3.9
Requires-Python: ~=3.8
License-File: LICENSE.txt
License-File: NOTICE
Requires-Dist: backoff (>=1.8.0)
Requires-Dist: bleach (<4.0.0,>=3.0.2)
Requires-Dist: cachelib (<0.5,>=0.4.1)
Requires-Dist: celery (<6.0.0,>=5.2.2)
Requires-Dist: click (>=8.0.3)
Requires-Dist: colorama
Requires-Dist: croniter (>=0.3.28)
Requires-Dist: cron-descriptor
Requires-Dist: cryptography (>=3.3.2)
Requires-Dist: deprecation (<2.2.0,>=2.1.0)
Requires-Dist: flask (<3.0.0,>=2.0.0)
Requires-Dist: flask-appbuilder (<5.0.0,>=4.1.3)
Requires-Dist: flask-caching (>=1.10.0)
Requires-Dist: flask-compress
Requires-Dist: flask-talisman
Requires-Dist: flask-migrate
Requires-Dist: flask-wtf
Requires-Dist: func-timeout
Requires-Dist: geopy
Requires-Dist: graphlib-backport
Requires-Dist: gunicorn (>=20.1.0)
Requires-Dist: hashids (<2,>=1.3.1)
Requires-Dist: holidays (==0.14.2)
Requires-Dist: humanize
Requires-Dist: isodate
Requires-Dist: markdown (>=3.0)
Requires-Dist: msgpack (<1.1,>=1.0.0)
Requires-Dist: numpy (==1.22.1)
Requires-Dist: pandas (<1.4,>=1.3.0)
Requires-Dist: parsedatetime
Requires-Dist: pgsanity
Requires-Dist: polyline
Requires-Dist: pyparsing (<4,>=3.0.6)
Requires-Dist: python-dateutil
Requires-Dist: python-dotenv
Requires-Dist: python-geohash
Requires-Dist: pyarrow (<6.0,>=5.0.0)
Requires-Dist: pyyaml (>=5.4)
Requires-Dist: PyJWT (<3.0,>=2.4.0)
Requires-Dist: redis
Requires-Dist: selenium (>=3.141.0)
Requires-Dist: simplejson (>=3.15.0)
Requires-Dist: slackclient (==2.5.0)
Requires-Dist: sqlalchemy (!=1.3.21,<1.4,>=1.3.16)
Requires-Dist: sqlalchemy-utils (<0.38,>=0.37.8)
Requires-Dist: sqlparse (==0.3.0)
Requires-Dist: tabulate (==0.8.9)
Requires-Dist: typing-extensions (<4,>=3.10)
Requires-Dist: wtforms-json
Provides-Extra: athena
Requires-Dist: pyathena (<1.11,>=1.10.8) ; extra == 'athena'
Provides-Extra: aurora-data-api
Requires-Dist: preset-sqlalchemy-aurora-data-api (<0.3,>=0.2.8) ; extra == 'aurora-data-api'
Provides-Extra: bigquery
Requires-Dist: pandas-gbq (>=0.10.0) ; extra == 'bigquery'
Requires-Dist: pybigquery (>=0.4.10) ; extra == 'bigquery'
Requires-Dist: google-cloud-bigquery (>=2.4.0) ; extra == 'bigquery'
Provides-Extra: clickhouse
Requires-Dist: clickhouse-sqlalchemy (<0.2,>=0.1.4) ; extra == 'clickhouse'
Provides-Extra: cockroachdb
Requires-Dist: cockroachdb (<0.4,>=0.3.5) ; extra == 'cockroachdb'
Provides-Extra: cors
Requires-Dist: flask-cors (>=2.0.0) ; extra == 'cors'
Provides-Extra: crate
Requires-Dist: crate[sqlalchemy] (<0.27,>=0.26.0) ; extra == 'crate'
Provides-Extra: databricks
Requires-Dist: databricks-sql-connector (<3,>=2.0.2) ; extra == 'databricks'
Requires-Dist: sqlalchemy-databricks (>=0.2.0) ; extra == 'databricks'
Provides-Extra: db2
Requires-Dist: ibm-db-sa (<0.4,>=0.3.5) ; extra == 'db2'
Provides-Extra: dremio
Requires-Dist: sqlalchemy-dremio (<1.3,>=1.1.5) ; extra == 'dremio'
Provides-Extra: drill
Requires-Dist: sqlalchemy-drill (==0.1.dev) ; extra == 'drill'
Provides-Extra: druid
Requires-Dist: pydruid (<0.7,>=0.6.1) ; extra == 'druid'
Provides-Extra: elasticsearch
Requires-Dist: elasticsearch-dbapi (<0.3.0,>=0.2.0) ; extra == 'elasticsearch'
Provides-Extra: exasol
Requires-Dist: sqlalchemy-exasol (<3.0,>=2.4.0) ; extra == 'exasol'
Provides-Extra: excel
Requires-Dist: xlrd (<1.3,>=1.2.0) ; extra == 'excel'
Provides-Extra: firebird
Requires-Dist: sqlalchemy-firebird (<0.8,>=0.7.0) ; extra == 'firebird'
Provides-Extra: firebolt
Requires-Dist: firebolt-sqlalchemy (>=0.0.1) ; extra == 'firebolt'
Provides-Extra: gsheets
Requires-Dist: shillelagh[gsheetsapi] (<2,>=1.0.14) ; extra == 'gsheets'
Provides-Extra: hana
Requires-Dist: hdbcli (==2.4.162) ; extra == 'hana'
Requires-Dist: sqlalchemy-hana (==0.4.0) ; extra == 'hana'
Provides-Extra: hive
Requires-Dist: pyhive[hive] (>=0.6.5) ; extra == 'hive'
Requires-Dist: tableschema ; extra == 'hive'
Requires-Dist: thrift (<1.0.0,>=0.11.0) ; extra == 'hive'
Provides-Extra: impala
Requires-Dist: impyla (<0.17,>0.16.2) ; extra == 'impala'
Provides-Extra: kusto
Requires-Dist: sqlalchemy-kusto (<2,>=1.0.1) ; extra == 'kusto'
Provides-Extra: kylin
Requires-Dist: kylinpy (<2.9,>=2.8.1) ; extra == 'kylin'
Provides-Extra: mssql
Requires-Dist: pymssql (<2.2,>=2.1.4) ; extra == 'mssql'
Provides-Extra: mysql
Requires-Dist: mysqlclient (<3,>=2.1.0) ; extra == 'mysql'
Provides-Extra: netezza
Requires-Dist: nzalchemy (>=11.0.2) ; extra == 'netezza'
Provides-Extra: oracle
Requires-Dist: cx-Oracle (<8.1,>8.0.0) ; extra == 'oracle'
Provides-Extra: pinot
Requires-Dist: pinotdb (<0.4,>=0.3.3) ; extra == 'pinot'
Provides-Extra: postgres
Requires-Dist: psycopg2-binary (==2.9.1) ; extra == 'postgres'
Provides-Extra: presto
Requires-Dist: pyhive[presto] (>=0.6.5) ; extra == 'presto'
Provides-Extra: prophet
Requires-Dist: prophet (<1.1,>=1.0.1) ; extra == 'prophet'
Requires-Dist: pystan (<3.0) ; extra == 'prophet'
Provides-Extra: redshift
Requires-Dist: sqlalchemy-redshift (<0.9,>=0.8.1) ; extra == 'redshift'
Provides-Extra: rockset
Requires-Dist: rockset (<0.9,>=0.8.10) ; extra == 'rockset'
Provides-Extra: shillelagh
Requires-Dist: shillelagh[datasetteapi,gsheetsapi,socrata,weatherapi] (<2,>=1.0.3) ; extra == 'shillelagh'
Provides-Extra: snowflake
Requires-Dist: snowflake-sqlalchemy (==1.2.4) ; extra == 'snowflake'
Provides-Extra: solr
Requires-Dist: sqlalchemy-solr (>=0.2.0) ; extra == 'solr'
Provides-Extra: teradata
Requires-Dist: teradatasql (>=16.20.0.23) ; extra == 'teradata'
Provides-Extra: thumbnails
Requires-Dist: Pillow (<10.0.0,>=9.0.1) ; extra == 'thumbnails'
Provides-Extra: trino
Requires-Dist: trino (>=0.313.0) ; extra == 'trino'
Provides-Extra: vertica
Requires-Dist: sqlalchemy-vertica-python (<0.6,>=0.5.9) ; extra == 'vertica'
